hop/plugins/snews.py
hop_plugin_snews-0.0.1.dist-info/LICENSE
hop_plugin_snews-0.0.1.dist-info/METADATA
hop_plugin_snews-0.0.1.dist-info/WHEEL
hop_plugin_snews-0.0.1.dist-info/entry_points.txt
hop_plugin_snews-0.0.1.dist-info/top_level.txt
hop_plugin_snews-0.0.1.dist-info/RECORD
