Metadata-Version: 2.1
Name: hop-plugin-snews
Version: 0.0.1
Summary: A hop-client plugin for SNEWS.
Home-page: https://github.com/SNEWS2/hop-plugin-snews
Author: Patrick Godwin
Author-email: patrick.godwin@psu.edu
License: BSD 3-Clause
Platform: UNKNOWN
Classifier: Development Status :: 2 - Pre-Alpha
Classifier: Programming Language :: Python
Classifier: Programming Language :: Python :: 3
Classifier: Intended Audience :: Science/Research
Classifier: Intended Audience :: Developers
Classifier: Natural Language :: English
Classifier: Topic :: Scientific/Engineering
Classifier: Topic :: Scientific/Engineering :: Astronomy
Classifier: Topic :: Scientific/Engineering :: Physics
Classifier: Operating System :: POSIX
Classifier: Operating System :: Unix
Classifier: Operating System :: MacOS
Classifier: License :: OSI Approved :: BSD License
Requires-Python: >=3.6.*
Requires-Dist: hop-client (>=0.2)
Provides-Extra: dev
Requires-Dist: autopep8 ; extra == 'dev'
Requires-Dist: flake8 ; extra == 'dev'
Requires-Dist: pytest (<5.4,>=5.0) ; extra == 'dev'
Requires-Dist: pytest-console-scripts ; extra == 'dev'
Requires-Dist: pytest-cov ; extra == 'dev'
Provides-Extra: docs
Requires-Dist: sphinx ; extra == 'docs'
Requires-Dist: sphinx-rtd-theme ; extra == 'docs'
Requires-Dist: sphinxcontrib-programoutput ; extra == 'docs'
